LICENSE
README.md
setup.py
airflow_provider_vdk.egg-info/PKG-INFO
airflow_provider_vdk.egg-info/SOURCES.txt
airflow_provider_vdk.egg-info/dependency_links.txt
airflow_provider_vdk.egg-info/entry_points.txt
airflow_provider_vdk.egg-info/requires.txt
airflow_provider_vdk.egg-info/top_level.txt
vdk_provider/__init__.py
vdk_provider/hooks/__init__.py
vdk_provider/hooks/vdk.py
vdk_provider/operators/__init__.py
vdk_provider/operators/vdk.py
vdk_provider/sensors/__init__.py
vdk_provider/sensors/vdk.py