Metadata-Version: 2.1
Name: airflow-provider-vdk
Version: 0.0.576069739
Summary: Airflow provider for Versatile Data Kit.
Home-page: https://github.com/vmware/versatile-data-kit
Author: Versatile Data Kit Development Team
Author-email: versatile-data-kit@vmware.com
License: Apache License 2.0
Requires-Python: ~=3.7
License-File: LICENSE
